samadi/__init__.py
samadi/a1.py
samadi/a2.py
samadi/a3.py
samadi-0.0.1.dist-info/LICENSE
samadi-0.0.1.dist-info/METADATA
samadi-0.0.1.dist-info/WHEEL
samadi-0.0.1.dist-info/top_level.txt
samadi-0.0.1.dist-info/RECORD
