Metadata-Version: 2.1
Name: samadi
Version: 0.0.1
Summary: samadi
Home-page: UNKNOWN
Author: samADI
Author-email: adityaharikumar3@gmail.com
License: UNKNOWN
Keywords: samadi,samADI,adi,python tutorial
Platform: UNKNOWN
Classifier: Development Status :: 1 - Planning
Classifier: Intended Audience :: Developers
Classifier: Programming Language :: Python :: 3
Classifier: Operating System :: Unix
Classifier: Operating System :: MacOS :: MacOS X
Classifier: Operating System :: Microsoft :: Windows
License-File: LICENSE
